home_service/__init__.py
home_service/app.py
home_service/config.py
home_service/core.py
home_service/endpoints/__init__.py
home_service/endpoints/sensor_blueprint.py
home_service/models/__init__.py
home_service/models/base.py
home_service/models/devices.py
home_service/models/room_humidity.py
home_service/models/room_temp.py
home_service/models/server_temp.py
home_service/static/android-chrome-192x192.png
home_service/static/android-chrome-512x512.png
home_service/static/apple-touch-icon.png
home_service/static/favicon-16x16.png
home_service/static/favicon-32x32.png
home_service/static/favicon.ico
home_service/static/safari-pinned-tab.svg
home_service/static/site.webmanifest
home_service/static/css/custom.min.css
home_service/static/js/chart-area.js
home_service/static/js/chart-bar.js
home_service/static/js/chart-pie.js
home_service/static/js/main-client.js
home_service/static/js/mixin.js
home_service/static/js/sb-admin-2.js
home_service/static/vendor/bootstrap.bundle.min.js
home_service/static/vendor/jquery.easing.min.js
home_service/static/vendor/jquery.min.js
home_service/templates/debug.html
home_service/templates/index.html
home_service-0.2.2.data/scripts/home-service
home_service-0.2.2.dist-info/LICENSE
home_service-0.2.2.dist-info/METADATA
home_service-0.2.2.dist-info/WHEEL
home_service-0.2.2.dist-info/top_level.txt
home_service-0.2.2.dist-info/RECORD
