Metadata-Version: 2.1
Name: home-service
Version: 0.2.2
Summary: A simple home monitoring system
Home-page: https://github.com/tiega/home-service-v2
Author: Tiger Nie
Author-email: nhl0819@gmail.com
Maintainer: Tiger Nie
Maintainer-email: nhl0819@gmail.com
License: MIT
Platform: UNKNOWN
Classifier: License :: OSI Approved :: MIT License
Classifier: Development Status :: 3 - Alpha
Classifier: Framework :: Flask
Classifier: Operating System :: Unix
Classifier: Operating System :: POSIX
Classifier: Operating System :: MacOS
Requires-Python: >=3.6
Requires-Dist: Flask (>=1.1.1)
Requires-Dist: flask-sqlalchemy (>=2.4.1)
Requires-Dist: SQLAlchemy (>=1.3)
Requires-Dist: gunicorn (>=20.0)
Provides-Extra: dev
Requires-Dist: black (==19.10b0) ; extra == 'dev'
Requires-Dist: coverage (>=4.5.4) ; extra == 'dev'
Requires-Dist: pytest (>=5.2.0) ; extra == 'dev'
Requires-Dist: python-dotenv ; extra == 'dev'
